data_warehouse_client/__init__.py
data_warehouse_client/auto_generate_test_cases.py
data_warehouse_client/auto_generate_tests.py
data_warehouse_client/check_bounded_values.py
data_warehouse_client/check_for_datetime_table.py
data_warehouse_client/clone_study_metadata.py
data_warehouse_client/csv_io.py
data_warehouse_client/data_warehouse.py
data_warehouse_client/delete_study_contents.py
data_warehouse_client/file_utils.py
data_warehouse_client/import_tests.py
data_warehouse_client/import_with_checks.py
data_warehouse_client/load_data.py
data_warehouse_client/load_warehouse_helpers.py
data_warehouse_client/loader_tests.py
data_warehouse_client/multiple_mg_inserts.py
data_warehouse_client/plot.py
data_warehouse_client/print_io.py
data_warehouse_client/print_metadata_table.py
data_warehouse_client/study_profile.py
data_warehouse_client/study_summary.py
data_warehouse_client/table_reader_json.py
data_warehouse_client/table_writer_json.py
data_warehouse_client/transform_result_format.py
data_warehouse_client/type_checks.py
data_warehouse_client/type_definitions.py
data_warehouse_client/warehouse_checker.py
data_warehouse_client/sql/bounded_datetime_measurement_types_without_bounds.sql
data_warehouse_client/sql/bounded_datetimes.sql
data_warehouse_client/sql/bounded_integer_measurement_types_without_bounds.sql
data_warehouse_client/sql/bounded_integers.sql
data_warehouse_client/sql/bounded_real_measurement_types_without_bounds.sql
data_warehouse_client/sql/bounded_reals.sql
data_warehouse_client/sql/core_sql_from_for_measurements.sql
data_warehouse_client/sql/core_sql_select_for_measurements.sql
data_warehouse_client/sql/get_all_measurement_groups.sql
data_warehouse_client/sql/get_all_measurement_groups_and_types_in_a_study.sql
data_warehouse_client/sql/get_all_table_names.sql
data_warehouse_client/sql/get_boundsdatetime_in_study.sql
data_warehouse_client/sql/get_boundsint_in_study.sql
data_warehouse_client/sql/get_boundsreal_in_study.sql
data_warehouse_client-3.0.7.dist-info/LICENSE
data_warehouse_client-3.0.7.dist-info/METADATA
data_warehouse_client-3.0.7.dist-info/WHEEL
data_warehouse_client-3.0.7.dist-info/top_level.txt
data_warehouse_client-3.0.7.dist-info/RECORD
