Metadata-Version: 2.1
Name: data-warehouse-client
Version: 3.0.7
Summary: This package provides access to the e-Science Central data warehouse that can be used to store, access and analyse data collected in scientific studies, including for healthcare applications
Home-page: https://github.com/e-science-central/data-warehouse-client
Author: Paul Watson
Author-email: paul.watson@ncl.ac.uk
Classifier: Programming Language :: Python :: 3
Classifier: License :: OSI Approved :: Apache Software License
Classifier: Operating System :: OS Independent
Requires-Python: >=3.6
License-File: LICENSE
Requires-Dist: more-itertools
Requires-Dist: matplotlib
Requires-Dist: psycopg2
Requires-Dist: tabulate
